avfilters/__init__.py
avfilters/concatenate.py
avfilters/inspect.py
avfilters/remux.py
avfilters/reverse.py
avfilters-0.0.1.dist-info/LICENSE.md
avfilters-0.0.1.dist-info/METADATA
avfilters-0.0.1.dist-info/WHEEL
avfilters-0.0.1.dist-info/top_level.txt
avfilters-0.0.1.dist-info/RECORD
