Metadata-Version: 2.1
Name: avfilters
Version: 0.0.1
Summary: Common Audio and Video filters
Author-email: Jérome Eertmans <jeertmans@icloud.com>
License: MIT
Project-URL: Changelog, https://github.com/jeertmans/avfilters/releases
Project-URL: Documentation, https://avfilters.readthedocs.io/
Project-URL: Founding, https://github.com/sponsors/jeertmans
Project-URL: Homepage, https://github.com/jeertmans/avfilters
Project-URL: Repository, https://github.com/jeertmans/avfilters
Keywords: libav,ffmpeg,audio,video,filters
Classifier: Intended Audience :: Developers
Classifier: License :: OSI Approved :: MIT License
Classifier: Natural Language :: English
Classifier: Operating System :: MacOS :: MacOS X
Classifier: Operating System :: POSIX
Classifier: Operating System :: Unix
Classifier: Operating System :: Microsoft :: Windows
Classifier: Programming Language :: Cython
Classifier: Programming Language :: Python :: 3.8
Classifier: Programming Language :: Python :: 3.9
Classifier: Programming Language :: Python :: 3.10
Classifier: Programming Language :: Python :: 3.11
Classifier: Programming Language :: Python :: 3.12
Classifier: Topic :: Software Development :: Libraries :: Python Modules
Classifier: Topic :: Multimedia :: Sound/Audio
Classifier: Topic :: Multimedia :: Sound/Audio :: Conversion
Classifier: Topic :: Multimedia :: Video
Classifier: Topic :: Multimedia :: Video :: Conversion
Requires-Python: >=3.8
License-File: LICENSE.md
Requires-Dist: av >=9.0.0
Provides-Extra: dev
Requires-Dist: pre-commit >=3.5.0 ; extra == 'dev'
Provides-Extra: docs
Requires-Dist: sphinx >=6 ; extra == 'docs'
Requires-Dist: sphinx-book-theme >=1 ; extra == 'docs'
Requires-Dist: sphinx-autodoc-typehints >=1 ; extra == 'docs'
Requires-Dist: sphinx-copybutton >=0.5.2 ; extra == 'docs'
Requires-Dist: sphinxext-opengraph >=0.9.1 ; extra == 'docs'
Provides-Extra: test
Requires-Dist: numpy >=1.24.4 ; extra == 'test'
Requires-Dist: pytest >=8.1.1 ; extra == 'test'
Requires-Dist: pytest-cov >=4.1.0 ; extra == 'test'
